DIRAC/__init__.py
DIRAC/AccountingSystem/ConfigTemplate.cfg
DIRAC/AccountingSystem/__init__.py
DIRAC/AccountingSystem/Agent/NetworkAgent.py
DIRAC/AccountingSystem/Agent/__init__.py
DIRAC/AccountingSystem/Agent/test/Test_NetworkAgent.py
DIRAC/AccountingSystem/Client/AccountingCLI.py
DIRAC/AccountingSystem/Client/DataStoreClient.py
DIRAC/AccountingSystem/Client/ReportCLI.py
DIRAC/AccountingSystem/Client/ReportsClient.py
DIRAC/AccountingSystem/Client/__init__.py
DIRAC/AccountingSystem/Client/Types/BaseAccountingType.py
DIRAC/AccountingSystem/Client/Types/DataOperation.py
DIRAC/AccountingSystem/Client/Types/Job.py
DIRAC/AccountingSystem/Client/Types/Network.py
DIRAC/AccountingSystem/Client/Types/Pilot.py
DIRAC/AccountingSystem/Client/Types/PilotSubmission.py
DIRAC/AccountingSystem/Client/Types/StorageOccupancy.py
DIRAC/AccountingSystem/Client/Types/WMSHistory.py
DIRAC/AccountingSystem/Client/Types/__init__.py
DIRAC/AccountingSystem/DB/AccountingDB.py
DIRAC/AccountingSystem/DB/AccountingDB.sql
DIRAC/AccountingSystem/DB/MultiAccountingDB.py
DIRAC/AccountingSystem/DB/__init__.py
DIRAC/AccountingSystem/DB/test/Test_AccountingDB.py
DIRAC/AccountingSystem/Service/DataStoreHandler.py
DIRAC/AccountingSystem/Service/ReportGeneratorHandler.py
DIRAC/AccountingSystem/Service/__init__.py
DIRAC/AccountingSystem/private/DBUtils.py
DIRAC/AccountingSystem/private/MainReporter.py
DIRAC/AccountingSystem/private/__init__.py
DIRAC/AccountingSystem/private/Plotters/BaseReporter.py
DIRAC/AccountingSystem/private/Plotters/DataOperationPlotter.py
DIRAC/AccountingSystem/private/Plotters/JobPlotter.py
DIRAC/AccountingSystem/private/Plotters/NetworkPlotter.py
DIRAC/AccountingSystem/private/Plotters/PilotPlotter.py
DIRAC/AccountingSystem/private/Plotters/PilotSubmissionPlotter.py
DIRAC/AccountingSystem/private/Plotters/StorageOccupancyPlotter.py
DIRAC/AccountingSystem/private/Plotters/WMSHistoryPlotter.py
DIRAC/AccountingSystem/private/Plotters/__init__.py
dirac-9.0.16.dist-info/licenses/LICENSE
dirac-9.0.16.dist-info/METADATA
dirac-9.0.16.dist-info/WHEEL
dirac-9.0.16.dist-info/entry_points.txt
dirac-9.0.16.dist-info/top_level.txt
dirac-9.0.16.dist-info/RECORD
