Metadata-Version: 2.4
Name: DIRAC
Version: 9.0.16
Summary: DIRAC is an interware, meaning a software framework for distributed computing.
Home-page: https://github.com/DIRACGrid/DIRAC/
License: GPL-3.0-only
Classifier: Development Status :: 5 - Production/Stable
Classifier: Intended Audience :: Science/Research
Classifier: License :: OSI Approved :: GNU General Public License v3 (GPLv3)
Classifier: Programming Language :: Python :: 3
Classifier: Programming Language :: Python :: 3.11
Classifier: Topic :: Scientific/Engineering
Classifier: Topic :: System :: Distributed Computing
Requires-Python: >=3.11
License-File: LICENSE
Requires-Dist: boto3>=1.35
Requires-Dist: botocore>=1.35
Requires-Dist: cachetools
Requires-Dist: certifi
Requires-Dist: cwltool
Requires-Dist: diraccfg
Requires-Dist: DIRACCommon==v9.0.16
Requires-Dist: diracx-client>=v0.0.1
Requires-Dist: diracx-core>=v0.0.1
Requires-Dist: diracx-cli>=v0.0.1
Requires-Dist: db12
Requires-Dist: fts3
Requires-Dist: gfal2-python
Requires-Dist: importlib_metadata>=4.4
Requires-Dist: importlib_resources
Requires-Dist: M2Crypto>=0.36
Requires-Dist: packaging
Requires-Dist: pexpect
Requires-Dist: prompt-toolkit>=3
Requires-Dist: psutil
Requires-Dist: pyasn1
Requires-Dist: pyasn1-modules
Requires-Dist: pydantic>=2.4
Requires-Dist: pyparsing
Requires-Dist: python-dateutil
Requires-Dist: pytz
Requires-Dist: requests
Requires-Dist: rucio-clients>=34.4.2
Requires-Dist: sqlalchemy
Requires-Dist: typing_extensions>=4.3.0
Requires-Dist: Authlib>=1.0.0.a2
Requires-Dist: pyjwt
Requires-Dist: dominate
Requires-Dist: zstandard
Requires-Dist: xattr
Provides-Extra: server
Requires-Dist: CMRESHandler; extra == "server"
Requires-Dist: opensearch-py; extra == "server"
Requires-Dist: GitPython; extra == "server"
Requires-Dist: ldap3; extra == "server"
Requires-Dist: apache-libcloud; extra == "server"
Requires-Dist: matplotlib; extra == "server"
Requires-Dist: mysqlclient; extra == "server"
Requires-Dist: numpy; extra == "server"
Requires-Dist: pillow; extra == "server"
Requires-Dist: python-json-logger; extra == "server"
Requires-Dist: pyyaml; extra == "server"
Requires-Dist: stomp.py; extra == "server"
Requires-Dist: suds; extra == "server"
Requires-Dist: tornado~=5.1.1; extra == "server"
Requires-Dist: tornado-m2crypto; extra == "server"
Requires-Dist: importlib_resources; extra == "server"
Provides-Extra: testing
Requires-Dist: hypothesis; extra == "testing"
Requires-Dist: mock; extra == "testing"
Requires-Dist: parameterized; extra == "testing"
Requires-Dist: pytest; extra == "testing"
Requires-Dist: pytest-cov; extra == "testing"
Requires-Dist: pytest-mock; extra == "testing"
Requires-Dist: pytest-rerunfailures; extra == "testing"
Requires-Dist: pycodestyle; extra == "testing"
Dynamic: license-file
